[
  {
    "uuid": "6112869cf0d1326bc2b4bed9",
    "parentId": "6112869cf0d1326bc2b4bed8",
    "label": "Level_1",
    "definition": "Shells have Byne’s disease. Specimens (of any kind) have signs of pest infestation. Insect specimens have fallen off of pin. Specimens are damaged to the point of being unusable",
    "children": []
  },
  {
    "uuid": "6112869cf0d1326bc2b4beda",
    "parentId": "6112869cf0d1326bc2b4bed8",
    "label": "Level_2",
    "definition": "Specimens are damaged: broken into multiple pieces, with past pest damage, loose teeth or bones. Insect pins are broken or significantly bent.",
    "children": []
  },
  {
    "uuid": "6112869df0d1326bc2b4bedb",
    "parentId": "6112869cf0d1326bc2b4bed8",
    "label": "Level_3",
    "definition": "All specimens are intact and stable.",
    "children": []
  }
]