{
  "citation": {
    "date": [
      {
        "date": "2023-09-08 13:19:13",
        "dateType": "revision"
      }
    ],
    "description": "No description available.",
    "title": "Global Change Master Directory (GCMD) Measurement Name",
    "edition": "Version 16.9",
    "onlineResource": [
      {
        "uri": "https://gcmd.earthdata.nasa.gov/kms/concept/2bc6e372-93d8-4672-96b1-ec159aff2e19?format=json"
      }
    ],
    "identifier": [
      {
        "identifier": "2bc6e372-93d8-4672-96b1-ec159aff2e19"
      }
    ]
  },
  "keywordType": "MeasurementName",
  "label": "Measurement Name",
  "keywords": null,
  "keywordsUrl": "https://cdn.jsdelivr.net/gh/adiwg/mdKeywords@test-dev/resources/keywords/gcmd-2bc6e372-93d8-4672-96b1-ec159aff2e19.json"
}